Metadata-Version: 2.1
Name: epicfilemanager
Version: 0.1.0
Summary: File manager
Author: Epic099
Author-email: 
Classifier: Programming Language :: Python :: 3
Classifier: License :: OSI Approved :: MIT License
Classifier: Operating System :: OS Independent
Requires-Python: >=3.6
